mixin_sdk/__init__.py
mixin_sdk/auth.py
mixin_sdk/conversation.py
mixin_sdk/get_snapshots.py
mixin_sdk/globalval.py
mixin_sdk/mixin_ws_api.py
mixin_sdk/request.py
mixin_sdk/user.py
mixin_sdk_py3-0.0.2.dist-info/METADATA
mixin_sdk_py3-0.0.2.dist-info/WHEEL
mixin_sdk_py3-0.0.2.dist-info/top_level.txt
mixin_sdk_py3-0.0.2.dist-info/RECORD
