Metadata-Version: 2.1
Name: mixin-sdk-py3
Version: 0.0.2
Summary: An python3 sdk to mixin network
Home-page: https://github.com/lilasxie/mixin_sdk_py3
Author: lilasxie
Author-email: thanklilas@163.com
Maintainer: lilasxie
Maintainer-email: thanklilas@163.com
Classifier: Programming Language :: Python :: 3
Classifier: License :: OSI Approved :: MIT License
Classifier: Operating System :: OS Independent
Requires-Python: >=3.5
